{
  "basics": {
    "name": "Muntasir Wahed",
    "label": "",
    "picture": "https://avatars0.githubusercontent.com/u/12914001?s=460&v=4",
    "email": "wahedmuntasir@gmail.com",
    "phone": "880-*********",
    "website": "https://immuntasir.github.io",
    "summary": "I have completed B.Sc in Computer Science and Engineering from the Department of Computer Science and Engineering at the University of Dhaka, Bangladesh. I am currently employed as a Software Engineer at Enosis Solutions. <strong>PS: This site is not complete yet. I am trying to upload my projects as soon as possible!</strong>",
    "location": {
      "address": "",
      "postalCode": "1203",
      "city": "Dhaka",
      "countryCode": "BD",
      "region": "Bangladesh"
    },
    "profiles": [
      {
        "network": "github",
        "username": "immuntasir",
        "url": "http://github.com/immuntasir"
      },
      {
        "network": "linkedin",
        "username": "immuntasir",
        "url": "http://linkedin.com/in/immuntasir"
      },
      {
        "network": "twitter",
        "username": "immuntasir",
        "url": "http://twitter.com/immuntasir"
      },
      {
        "network": "instagram",
        "username": "immuntasir",
        "url": "http://instagram.com/immuntasir"
      }
    ]
  },
  "interests": [
    {
      "name": "Natural Language Processing",
      "keywords": [
      ]
    },
    {
      "name": "Data Mining",
      "keywords": [
      ]
    },
    {
      "name": "Machine Learning",
      "keywords": [
      ]
    },
    {
      "name": "Artificial Intelligence",
      "keywords": [
      ]
    }
  ],
  "skills": [
    {
      "name": "Languages and Frameworks",
      "level": "",
      "keywords": [
        "C",
        "Python",
        "Django",
        "Flask",
        "Java",
        "Javascript",
        "AngularJS"
      ]
    },
    {
      "name": "Toolsets/OS",
      "level": "",
      "keywords": [
        "Ubuntu",
        "Git/GitHub",
        "Windows"
      ]
    }
  ],
  "education": [
    {
      "institution": "University of Dhaka, Bangladesh",
      "area": "Computer Science and Engineering (December Spring, 2018)",
      "studyType": "B.Sc",
      "startDate": "2015-01-15",
      "endDate": "2018-12-31",
      "gpa": "3.66",
      "courses": [
      ]
    }
  ],
  "work": [
    {
      "company": "Enosis Solutions",
      "position": "Software Engineer",
      "website": "https://www.enosisbd.com/",
      "startDate": "2019-04-01",
      "endDate": "Present",
      "summary": "Frontend and Backend web development",
      "highlights": [
        "Frontend: HTML5, Sass, AngularJS",
        "Backend: Java (Spring)"
      ]
    },
    {
      "company": "Data and Design Lab",
      "position": "Research Assistant",
      "website": "https://www.dndlab.org/",
      "startDate": "2019-04-01",
      "endDate": "Present",
      "summary": "",
      "highlights": [
        "Data extraction and cleaning",
        "Data visualization"
      ]
    },
    {
      "company": "Beetles Cyber Security Ltd.",
      "position": "Intern",
      "website": "https://www.beetles.io/",
      "startDate": "2018-07-01",
      "endDate": "2018-11-31",
      "summary": "Developed and maintained the backend server",
      "highlights": [
        "Learned REST API",
        "Python (Django Framework)"
      ]
    }
  ],
  "volunteer": [
    {
      "organization": "CommunityAction",
      "website": "http://ca-bd.org/",
      "position": "Volunteer",
      "summary": "As a part of this organization, I volunteered to make the lives of under privileged children a bit better.",
      "highlights": [
        "collected donation and built a library for under privileged students with more than 500 books",
        "organized a motivation session for under privileged students"
      ]
    },
    {
      "organization": "https://www.7cups.com/",
      "website": "http://7cups.org/",
      "position": "Active Listener",
      "summary": "Active listening is the act of listening with empathy. I have always believed that mental health should be dealt with more care. As a part of this platform, I have worked on my active listening skill, which has made me a better person.",
      "highlights": [
        "hold more than 300 conversations",
        "helped more than 40 people"
      ]
    }
  ],
  "programmingcontests": [
    
  ],
  "references": [
    {
      "name": "Available upon request",
      "reference": ""
    }
  ]
}
